redis_instance.py
py_ztj_redis_instance-0.0.3.dist-info/METADATA
py_ztj_redis_instance-0.0.3.dist-info/WHEEL
py_ztj_redis_instance-0.0.3.dist-info/top_level.txt
py_ztj_redis_instance-0.0.3.dist-info/RECORD
