Metadata-Version: 2.1
Name: py-ztj-redis-instance
Version: 0.0.3
Summary: python redis instance package
Home-page: http://github.com/ztj1993/PythonPackages/blob/master/py_redis_instance
Author: ZhangTianJie
Author-email: ztj1993@gmail.com
License: MIT License
Keywords: redis
Platform: UNKNOWN
Requires-Dist: redis
Requires-Dist: py-ztj-registry
